celery_manager/__init__.py
celery_manager/main.py
celery_queue_manager-1.0.3.dist-info/METADATA
celery_queue_manager-1.0.3.dist-info/WHEEL
celery_queue_manager-1.0.3.dist-info/entry_points.txt
celery_queue_manager-1.0.3.dist-info/top_level.txt
celery_queue_manager-1.0.3.dist-info/RECORD
