Metadata-Version: 2.4
Name: celery-queue-manager
Version: 1.0.3
Summary: CLI tool to inspect and purge Celery Redis queues
Author-email: Machiel Broekman <maddogbroekman@gmail.com>
Requires-Python: >=3.7
Requires-Dist: redis
